soopervisor/__init__.py
soopervisor/_format.py
soopervisor/_io.py
soopervisor/abc.py
soopervisor/cli.py
soopervisor/config.py
soopervisor/enum.py
soopervisor/exceptions.py
soopervisor/exporter.py
soopervisor/validate.py
soopervisor/airflow/__init__.py
soopervisor/airflow/config.py
soopervisor/airflow/export.py
soopervisor/argo/__init__.py
soopervisor/argo/config.py
soopervisor/argo/export.py
soopervisor/assets/__init__.py
soopervisor/assets/airflow/bash.py
soopervisor/assets/airflow/docker.py
soopervisor/assets/airflow/kubernetes.py
soopervisor/assets/argo/__init__.py
soopervisor/assets/argo/template.yaml
soopervisor/assets/aws-lambda/Dockerfile
soopervisor/assets/aws-lambda/README.md
soopervisor/assets/aws-lambda/app.py
soopervisor/assets/aws-lambda/template.yaml
soopervisor/assets/aws-lambda/test_aws_lambda.py
soopervisor/assets/docker/Dockerfile
soopervisor/assets/kubeflow/Dockerfile
soopervisor/assets/slurm/template.sh
soopervisor/aws/__init__.py
soopervisor/aws/batch.py
soopervisor/aws/config.py
soopervisor/aws/lambda_.py
soopervisor/aws/util.py
soopervisor/commons/__init__.py
soopervisor/commons/conda.py
soopervisor/commons/dag.py
soopervisor/commons/dependencies.py
soopervisor/commons/docker.py
soopervisor/commons/source.py
soopervisor/kubeflow/__init__.py
soopervisor/kubeflow/config.py
soopervisor/kubeflow/export.py
soopervisor/shell/__init__.py
soopervisor/shell/config.py
soopervisor/shell/export.py
soopervisor-0.9.3.dist-info/LICENSE
soopervisor-0.9.3.dist-info/METADATA
soopervisor-0.9.3.dist-info/WHEEL
soopervisor-0.9.3.dist-info/entry_points.txt
soopervisor-0.9.3.dist-info/top_level.txt
soopervisor-0.9.3.dist-info/RECORD
