Metadata-Version: 2.1
Name: soopervisor
Version: 0.9.3
Home-page: https://github.com/ploomber/soopervisor
Author: 
Author-email: 
Classifier: Development Status :: 5 - Production/Stable
Classifier: Intended Audience :: Developers
Classifier: Intended Audience :: Science/Research
Classifier: License :: OSI Approved :: Apache Software License
Classifier: Operating System :: MacOS :: MacOS X
Classifier: Operating System :: Unix
Classifier: Operating System :: POSIX
Classifier: Operating System :: Microsoft :: Windows
Classifier: Programming Language :: Python
Classifier: Programming Language :: Python :: 3
Classifier: Programming Language :: Python :: 3.7
Classifier: Programming Language :: Python :: 3.8
Classifier: Programming Language :: Python :: 3.9
License-File: LICENSE
Requires-Dist: click
Requires-Dist: tqdm
Requires-Dist: pydantic
Requires-Dist: Jinja2
Requires-Dist: pyyaml
Requires-Dist: ploomber (>=0.14.6)
Requires-Dist: ploomber-core (>=0.0.11)
Requires-Dist: build
Provides-Extra: aws
Requires-Dist: boto3 ; extra == 'aws'
Provides-Extra: dev
Requires-Dist: pkgmt ; extra == 'dev'
Requires-Dist: invoke ; extra == 'dev'
Requires-Dist: pytest ; extra == 'dev'
Requires-Dist: Faker ; extra == 'dev'
Requires-Dist: yapf ; extra == 'dev'
Requires-Dist: flake8 ; extra == 'dev'
Requires-Dist: apache-airflow ; extra == 'dev'
Requires-Dist: apache-airflow-providers-cncf-kubernetes ; extra == 'dev'
Requires-Dist: apache-airflow-providers-docker ; extra == 'dev'
Requires-Dist: kfp ; extra == 'dev'
Requires-Dist: argo-workflows-dsl ; extra == 'dev'
Requires-Dist: moto (==1.3.14) ; extra == 'dev'
Requires-Dist: wheel ; extra == 'dev'
Requires-Dist: scikit-learn ; extra == 'dev'
Requires-Dist: sphinx ; extra == 'dev'
Requires-Dist: sphinx-autobuild ; extra == 'dev'
Requires-Dist: sphinx-inline-tabs ; extra == 'dev'
Requires-Dist: furo ; extra == 'dev'
Requires-Dist: twine ; extra == 'dev'
Requires-Dist: ipython ; extra == 'dev'
Requires-Dist: boto3 ; extra == 'dev'
